<?xml version="1.0" encoding="UTF-8"?>
<game audio="demo/LA/U2/L8-19/audio/combined.mp3,demo/LA/U2/L8-19/audio/combined.ogg" type="three-in-a-row">
  <title>Select a square. Then listen and choose.</title>
  <preload>
    <image>img/bg_players.jpg</image>
    <image>img/bg_player.png</image>
  </preload>
  <selectPlayer>
    <background>demo/LA/U2/L8-19/images/DRAM-Two-player-names.png</background>
  </selectPlayer>
  <screen>
    <players>
      <player>
        <background-color>​</background-color>
        <symbol h="150" w="150">img/symbol1.png</symbol>
      </player>
      <player>
        <background-color>​</background-color>
        <symbol h="150" w="150">img/symbol2.png</symbol>
      </player>
    </players>
    <items>
      <item>
        <question type="sound">1</question>
        <answers type="image">
          <answer solution="1">demo/LA/U2/L8-19/images/DRAMAIWB116.png</answer>
          <answer>demo/LA/U2/L8-19/images/DRAMAIWB117.png</answer>
          <answer>demo/LA/U2/L8-19/images/DRAMAIWB120.png</answer>
          <answer>demo/LA/U2/L8-19/images/DRAMAIWB121.png</answer>
        </answers>
      </item>
      <item>
        <question type="sound">2</question>
        <answers type="image">
          <answer solution="1">demo/LA/U2/L8-19/images/DRAMAIWB118.png</answer>
          <answer>demo/LA/U2/L8-19/images/DRAMAIWB119.png</answer>
          <answer>demo/LA/U2/L8-19/images/DRAMAIWB120.png</answer>
          <answer>demo/LA/U2/L8-19/images/DRAMAIWB117.png</answer>
        </answers>
      </item>
      <item>
        <question type="sound">3</question>
        <answers type="image">
          <answer solution="1">demo/LA/U2/L8-19/images/DRAMAIWB120.png</answer>
          <answer>demo/LA/U2/L8-19/images/DRAMAIWB121.png</answer>
          <answer>demo/LA/U2/L8-19/images/DRAMAIWB116.png</answer>
          <answer>demo/LA/U2/L8-19/images/DRAMAIWB117.png</answer>
        </answers>
      </item>
      <item>
        <question type="sound">4</question>
        <answers type="image">
          <answer solution="1">demo/LA/U2/L8-19/images/DRAMAIWB121.png</answer>
          <answer>demo/LA/U2/L8-19/images/DRAMAIWB116.png</answer>
          <answer>demo/LA/U2/L8-19/images/DRAMAIWB120.png</answer>
          <answer>demo/LA/U2/L8-19/images/DRAMAIWB117.png</answer>
        </answers>
      </item>
      <item>
        <question type="sound">5</question>
        <answers type="image">
          <answer solution="1">demo/LA/U2/L8-19/images/DRAMAIWB122.png</answer>
          <answer>demo/LA/U2/L8-19/images/DRAMAIWB123.png</answer>
          <answer>demo/LA/U2/L8-19/images/DRAMAIWB124.png</answer>
          <answer>demo/LA/U2/L8-19/images/DRAMAIWB125.png</answer>
        </answers>
      </item>
      <item>
        <question type="sound">6</question>
        <answers type="image">
          <answer solution="1">demo/LA/U2/L8-19/images/DRAMAIWB119.png</answer>
          <answer>demo/LA/U2/L8-19/images/DRAMAIWB118.png</answer>
          <answer>demo/LA/U2/L8-19/images/DRAMAIWB122.png</answer>
          <answer>demo/LA/U2/L8-19/images/DRAMAIWB124.png</answer>
        </answers>
      </item>
      <item>
        <question type="sound">7</question>
        <answers type="image">
          <answer solution="1">demo/LA/U2/L8-19/images/DRAMAIWB124.png</answer>
          <answer>demo/LA/U2/L8-19/images/DRAMAIWB125.png</answer>
          <answer>demo/LA/U2/L8-19/images/DRAMAIWB122.png</answer>
          <answer>demo/LA/U2/L8-19/images/DRAMAIWB123.png</answer>
        </answers>
      </item>
      <item>
        <question type="sound">8</question>
        <answers type="image">
          <answer solution="1">demo/LA/U2/L8-19/images/DRAMAIWB123.png</answer>
          <answer>demo/LA/U2/L8-19/images/DRAMAIWB124.png</answer>
          <answer>demo/LA/U2/L8-19/images/DRAMAIWB122.png</answer>
          <answer>demo/LA/U2/L8-19/images/DRAMAIWB125.png</answer>
        </answers>
      </item>
      <item>
        <question type="sound">9</question>
        <answers type="image">
          <answer solution="1">demo/LA/U2/L8-19/images/DRAMAIWB117.png</answer>
          <answer>demo/LA/U2/L8-19/images/DRAMAIWB120.png</answer>
          <answer>demo/LA/U2/L8-19/images/DRAMAIWB116.png</answer>
          <answer>demo/LA/U2/L8-19/images/DRAMAIWB121.png</answer>
        </answers>
      </item>
      <item>
        <question type="sound">10</question>
        <answers type="image">
          <answer solution="1">demo/LA/U2/L8-19/images/DRAMAIWB125.png</answer>
          <answer>demo/LA/U2/L8-19/images/DRAMAIWB122.png</answer>
          <answer>demo/LA/U2/L8-19/images/DRAMAIWB123.png</answer>
          <answer>demo/LA/U2/L8-19/images/DRAMAIWB124.png</answer>
        </answers>
      </item>
    </items>
  </screen>
  <sounds>
    <sound>
      <id>1</id>
      <start>0.20</start>
      <stop>1.16</stop>
    </sound>
    <sound>
      <id>2</id>
      <start>2.49</start>
      <stop>3.45</stop>
    </sound>
    <sound>
      <id>3</id>
      <start>4.81</start>
      <stop>5.83</stop>
    </sound>
    <sound>
      <id>4</id>
      <start>7.18</start>
      <stop>8.03</stop>
    </sound>
    <sound>
      <id>5</id>
      <start>9.37</start>
      <stop>10.92</stop>
    </sound>
    <sound>
      <id>6</id>
      <start>12.28</start>
      <stop>13.41</stop>
    </sound>
    <sound>
      <id>7</id>
      <start>14.76</start>
      <stop>16.29</stop>
    </sound>
    <sound>
      <id>8</id>
      <start>17.62</start>
      <stop>19.31</stop>
    </sound>
    <sound>
      <id>9</id>
      <start>20.67</start>
      <stop>21.60</stop>
    </sound>
    <sound>
      <id>10</id>
      <start>22.93</start>
      <stop>24.59</stop>
    </sound>
    <sound>
      <id>win</id>
      <start>26.01</start>
      <stop>30.68</stop>
    </sound>
    <sound>
      <id>yes</id>
      <start>32.49</start>
      <stop>34.17</stop>
    </sound>
    <sound>
      <id>no</id>
      <start>35.69</start>
      <stop>36.25</stop>
    </sound>
    <sound>
      <id>intro</id>
      <start>38.52</start>
      <stop>46.66</stop>
    </sound>
  </sounds>
  <popups>
    <win>
      <image>demo/LA/U2/L8-19/images/DRAM-Well-done-Times-Up-Robin.png</image>
      <text>It's a draw!</text>
      <winnerText>[placeholder] wins!</winnerText>
      <sound>win</sound>
    </win>
    <trophy>
      <image>demo/LA/U2/L8-19/images/DRAM-Well-done-Times-Up-Robin.png</image>
      <text>It's a draw!</text>
      <winnerText>[placeholder] wins!</winnerText>
      <sound>win</sound>
    </trophy>
  </popups>
</game>